pocketping/__init__.py
pocketping/core.py
pocketping/fastapi.py
pocketping/models.py
pocketping/storage.py
pocketping/webhooks.py
pocketping/ai/__init__.py
pocketping/ai/anthropic.py
pocketping/ai/base.py
pocketping/ai/gemini.py
pocketping/ai/openai.py
pocketping/bridges/__init__.py
pocketping/bridges/base.py
pocketping/bridges/discord.py
pocketping/bridges/slack.py
pocketping/bridges/telegram.py
pocketping/utils/__init__.py
pocketping/utils/ip_filter.py
pocketping/utils/user_agent_filter.py
pocketping-1.9.0.dist-info/METADATA
pocketping-1.9.0.dist-info/WHEEL
pocketping-1.9.0.dist-info/RECORD
