Metadata-Version: 2.4
Name: pocketping
Version: 1.9.0
Summary: Python SDK for PocketPing - real-time customer chat with mobile notifications
Project-URL: Homepage, https://github.com/Ruwad-io/pocketping
Project-URL: Documentation, https://github.com/Ruwad-io/pocketping/tree/main/packages/sdk-python#readme
Project-URL: Repository, https://github.com/Ruwad-io/pocketping
Author: PocketPing Contributors
License-Expression: MIT
Keywords: chat,discord,fastapi,notifications,slack,support,telegram
Classifier: Development Status :: 3 - Alpha
Classifier: Framework :: FastAPI
Classifier: Intended Audience :: Developers
Classifier: License :: OSI Approved :: MIT License
Classifier: Programming Language :: Python :: 3
Classifier: Programming Language :: Python :: 3.9
Classifier: Programming Language :: Python :: 3.10
Classifier: Programming Language :: Python :: 3.11
Classifier: Programming Language :: Python :: 3.12
Requires-Python: >=3.9
Requires-Dist: httpx>=0.25.0
Requires-Dist: pydantic>=2.0.0
Provides-Extra: ai
Requires-Dist: anthropic>=0.18.0; extra == 'ai'
Requires-Dist: google-generativeai>=0.3.0; extra == 'ai'
Requires-Dist: openai>=1.0.0; extra == 'ai'
Provides-Extra: all
Requires-Dist: anthropic>=0.18.0; extra == 'all'
Requires-Dist: discord-py>=2.3.0; extra == 'all'
Requires-Dist: fastapi>=0.100.0; extra == 'all'
Requires-Dist: google-generativeai>=0.3.0; extra == 'all'
Requires-Dist: openai>=1.0.0; extra == 'all'
Requires-Dist: python-telegram-bot>=20.0; extra == 'all'
Requires-Dist: slack-sdk>=3.23.0; extra == 'all'
Requires-Dist: websockets>=12.0; extra == 'all'
Provides-Extra: dev
Requires-Dist: httpx>=0.25.0; extra == 'dev'
Requires-Dist: pytest-asyncio>=0.21.0; extra == 'dev'
Requires-Dist: pytest-cov>=4.0.0; extra == 'dev'
Requires-Dist: pytest>=7.0.0; extra == 'dev'
Requires-Dist: ruff>=0.1.0; extra == 'dev'
Provides-Extra: discord
Requires-Dist: discord-py>=2.3.0; extra == 'discord'
Provides-Extra: fastapi
Requires-Dist: fastapi>=0.100.0; extra == 'fastapi'
Requires-Dist: websockets>=12.0; extra == 'fastapi'
Provides-Extra: slack
Requires-Dist: slack-sdk>=3.23.0; extra == 'slack'
Provides-Extra: telegram
Requires-Dist: python-telegram-bot>=20.0; extra == 'telegram'
